SolOrder/__init__.py
SolOrder/dihedral.py
SolOrder/entropy.py
SolOrder-1.0.0.dist-info/METADATA
SolOrder-1.0.0.dist-info/WHEEL
SolOrder-1.0.0.dist-info/top_level.txt
SolOrder-1.0.0.dist-info/RECORD
