Metadata-Version: 2.1
Name: SolOrder
Version: 1.0.0
Summary: An attempt to calculate structural order parameters of water molecules..
Home-page: https://github.com/dmighty007/SolOrder
Download-URL: https://github.com/dmighty007/SolOrder
Author: Dibyendu Maity
Author-email: dibyendumaity1999@bose.res.in
Keywords: water,SOL,Order,Parameter
